search_package/__init__.py
search_package/search.py
google_search_package-0.0.1.dist-info/METADATA
google_search_package-0.0.1.dist-info/WHEEL
google_search_package-0.0.1.dist-info/entry_points.txt
google_search_package-0.0.1.dist-info/top_level.txt
google_search_package-0.0.1.dist-info/RECORD
