Metadata-Version: 2.1
Name: google-search-package
Version: 0.0.1
Summary: This is a program that allows you to search the web from the comfort of your terminal.
Home-page: https://github.com/Dr-GameDev/Google-Search_Package
Author: Babalo Majiyezi
Author-email: raymondbabalo5@gmail.com
Classifier: Programming Language :: Python :: 3
Classifier: License :: OSI Approved :: MIT License
Classifier: Operating System :: OS Independent
Requires-Python: >=3.6
Requires-Dist: beautifulsoup4
Requires-Dist: requests
